12bucks-0.1.0.dist-info/licenses/LICENSE
finance/__init__.py
finance/admin.py
finance/apps.py
finance/forms.py
finance/models.py
finance/setup.py
finance/tests.py
finance/urls.py
finance/views.py
finance/migrations/0001_initial.py
finance/migrations/0002_miles.py
finance/migrations/0003_mileagerate.py
finance/migrations/0004_alter_transaction_receipt.py
finance/migrations/0005_remove_invoiceitem_invoice_numb_invoiceitem_invoice_and_more.py
finance/migrations/0006_alter_invoice_options_alter_invoiceitem_invoice_and_more.py
finance/migrations/__init__.py
finance/migrations/__pycache__/0001_initial.cpython-313.pyc
finance/migrations/__pycache__/0002_miles.cpython-313.pyc
finance/migrations/__pycache__/0003_mileagerate.cpython-313.pyc
finance/migrations/__pycache__/0004_alter_transaction_receipt.cpython-313.pyc
finance/migrations/__pycache__/0005_remove_invoiceitem_invoice_numb_invoiceitem_invoice_and_more.cpython-313.pyc
finance/migrations/__pycache__/0006_alter_invoice_options_alter_invoiceitem_invoice_and_more.cpython-313.pyc
finance/migrations/__pycache__/__init__.cpython-313.pyc
finance/templates/components/category_confirm_delete.html
finance/templates/components/category_form.html
finance/templates/components/client_confirm_delete.html
finance/templates/components/client_form.html
finance/templates/components/invoice_item.html
finance/templates/components/mileage_rate.html
finance/templates/components/sub_category_confirm_delete.html
finance/templates/components/sub_category_form.html
finance/templates/components/transaction_modal.html
finance/templates/components/unpaid_invoices.html
finance/templates/components/update_mileage_rate.html
finance/templates/finance/Invoice_edit copy.html
finance/templates/finance/Invoice_edit.html
finance/templates/finance/category_list.html
finance/templates/finance/category_summary.html
finance/templates/finance/category_summary_print.html
finance/templates/finance/client_list.html
finance/templates/finance/dashboard.html
finance/templates/finance/email_sent.html
12bucks-0.1.0.dist-info/METADATA
12bucks-0.1.0.dist-info/WHEEL
12bucks-0.1.0.dist-info/top_level.txt
12bucks-0.1.0.dist-info/RECORD
